abstract_solcatch/__init__.py
abstract_solcatch/utils.py
abstract_solcatch/database_calls/__init__.py
abstract_solcatch/database_calls/checkManager.py
abstract_solcatch/database_calls/solcatcherCalls.py
abstract_solcatch/solcatcher_funcs/__init__.py
abstract_solcatch/solcatcher_funcs/abstract_rate_limit.py
abstract_solcatch/solcatcher_funcs/api_calls.py
abstract_solcatch/solcatcher_funcs/requestFunctions.py
abstract_solcatch/solcatcher_funcs/unique_functions.py
abstract_solcatch/solcatcher_funcs/utilities.py
abstract_solcatch/solcatcher_funcs/utils.py
abstract_solcatcher/__init__.py
abstract_solcatcher/asyncUtils.py
abstract_solcatcher/dbCalls.py
abstract_solcatcher/tryapi.py
abstract_solcatcher/utils.py
abstract_solcatcher/database_calls/__init__.py
abstract_solcatcher/database_calls/checkManager.py
abstract_solcatcher/database_calls/solana_db_tables.json
abstract_solcatcher/database_calls/solcatcherCalls.py
abstract_solcatcher/dbConfig/__init__.py
abstract_solcatcher/dbConfig/db.py
abstract_solcatcher/dbConfig/dbCalls.py
abstract_solcatcher/dbConfig/dbCalls2.py
abstract_solcatcher/imageUtils/__init__.py
abstract_solcatcher/imageUtils/imageUtils.py
abstract_solcatcher/managers/__init__.py
abstract_solcatcher/managers/metDataManager.py
abstract_solcatcher/managers/metaDataManager.py
abstract_solcatcher/sniping/__init__.py
abstract_solcatcher/sniping/tryIt.py
abstract_solcatcher/sniping/pumpFun/__init__.py
abstract_solcatcher/sniping/pumpFun/dbFuncs.py
abstract_solcatcher/sniping/pumpFun/db_credentials.py
abstract_solcatcher/sniping/pumpFun/decode.py
abstract_solcatcher/sniping/pumpFun/idfs.py
abstract_solcatcher/sniping/pumpFun/logManager.py
abstract_solcatcher/sniping/pumpFun/programData.py
abstract_solcatcher/sniping/pumpFun/utils.py
abstract_solcatcher/sniping/pumpFun/websocketFuncs.py
abstract_solcatcher/solcatcher_api_calls/__init__.py
abstract_solcatcher/solcatcher_api_calls/main.py
abstract_solcatcher/solcatcher_api_calls/src/__init__.py
abstract_solcatcher-0.0.3.235.dist-info/METADATA
abstract_solcatcher-0.0.3.235.dist-info/WHEEL
abstract_solcatcher-0.0.3.235.dist-info/top_level.txt
abstract_solcatcher-0.0.3.235.dist-info/RECORD
