Metadata-Version: 2.4
Name: abstract_solcatcher
Version: 0.0.3.235
Summary: `abstract_solcatcher` provides a comprehensive solution for making HTTP requests specifically tailored for interacting with Solcatcher.io's APIs. It simplifies complex tasks such as data fetching, data manipulation, and interacting with the Flask backend of Solcatcher.io.
Home-page: https://github.com/AbstractEndeavors/abstract_solcatcher
Author: putkoff
Author-email: partners@abstractendeavors.com
License: MIT
Classifier: Development Status :: 3 - Alpha
Classifier: Intended Audience :: Developers
Classifier: Topic :: Software Development :: Libraries
Classifier: License :: OSI Approved :: MIT License
Classifier: Programming Language :: Python :: 3
Classifier: Programming Language :: Python :: 3.6
Classifier: Programming Language :: Python :: 3.7
Classifier: Programming Language :: Python :: 3.8
Classifier: Programming Language :: Python :: 3.9
Classifier: Typing :: Typed
Requires-Python: >=3.6
Requires-Dist: abstract_utilities
Requires-Dist: abstract_solana
Requires-Dist: abstract_apis
Requires-Dist: requests
Requires-Dist: abstract_security
Provides-Extra: dev
Requires-Dist: pytest; extra == "dev"
Requires-Dist: flake8; extra == "dev"
Requires-Dist: mypy; extra == "dev"
Dynamic: author
Dynamic: author-email
Dynamic: classifier
Dynamic: description
Dynamic: description-content-type
Dynamic: home-page
Dynamic: license
Dynamic: provides-extra
Dynamic: requires-dist
Dynamic: requires-python
Dynamic: summary
